bonsai_nn_library-0.5.1.dist-info/licenses/LICENSE.txt
nn_lib/__init__.py
nn_lib/env.py
nn_lib/trainer.py
nn_lib/analysis/__init__.py
nn_lib/analysis/pca.py
nn_lib/analysis/regression.py
nn_lib/analysis/kernels/__init__.py
nn_lib/analysis/kernels/base.py
nn_lib/analysis/kernels/brownian.py
nn_lib/analysis/kernels/linear.py
nn_lib/analysis/ntk/__init__.py
nn_lib/analysis/ntk/learnability.py
nn_lib/analysis/ntk/linearize.py
nn_lib/analysis/ntk/ntk.py
nn_lib/analysis/similarity/__init__.py
nn_lib/analysis/similarity/cka.py
nn_lib/datasets/__init__.py
nn_lib/datasets/base.py
nn_lib/datasets/cifar.py
nn_lib/datasets/coco_semantic_segmentation.py
nn_lib/datasets/enums.py
nn_lib/datasets/imagenet.py
nn_lib/datasets/mnist.py
nn_lib/datasets/transforms.py
nn_lib/jobs/__init__.py
nn_lib/jobs/dispatch.py
nn_lib/models/__init__.py
nn_lib/models/fancy_layers.py
nn_lib/models/graph_module_plus.py
nn_lib/models/graph_utils.py
nn_lib/models/lit_classifier.py
nn_lib/models/parametrizations.py
nn_lib/models/sparse_auto_encoder.py
nn_lib/models/utils.py
nn_lib/optim/__init__.py
nn_lib/optim/lr_finder.py
nn_lib/utils/__init__.py
nn_lib/utils/cli.py
nn_lib/utils/generic.py
nn_lib/utils/mlflow.py
bonsai_nn_library-0.5.1.dist-info/METADATA
bonsai_nn_library-0.5.1.dist-info/WHEEL
bonsai_nn_library-0.5.1.dist-info/top_level.txt
bonsai_nn_library-0.5.1.dist-info/RECORD
