Metadata-Version: 2.4
Name: bonsai-nn-library
Version: 0.5.1
Summary: Common PyTorch utilities for research projects on neural networks.
Author-email: Richard Lange <opensource@bonsai-neuro-ai.com>
License: MIT
Project-URL: Repository, https://github.com/bonsai-neuro-ai/nn-library
Classifier: Programming Language :: Python :: 3
Classifier: License :: OSI Approved :: MIT License
Classifier: Operating System :: OS Independent
Classifier: Development Status :: 1 - Planning
Classifier: Intended Audience :: Science/Research
Classifier: Topic :: Scientific/Engineering :: Artificial Intelligence
Requires-Python: >=3.10
License-File: LICENSE.txt
Requires-Dist: jsonargparse
Requires-Dist: lightning[pytorch-extra]
Requires-Dist: matplotlib
Requires-Dist: mlflow
Requires-Dist: numpy
Requires-Dist: pandas
Requires-Dist: parse
Requires-Dist: pycocotools
Requires-Dist: pydot
Requires-Dist: pyyaml
Requires-Dist: scikit-learn
Requires-Dist: scipy
Requires-Dist: seaborn
Requires-Dist: tabulate
Requires-Dist: torch
Requires-Dist: torchmetrics
Requires-Dist: torchvision
Requires-Dist: tqdm
Dynamic: license-file
